objectgmsh/__init__.py
objectgmsh/_version.py
objectgmsh/objects.py
objectgmsh/utils.py
objectgmsh/test/__init__.py
objectgmsh/test/test_objects.py
objectgmsh-0.11.dist-info/LICENSE
objectgmsh-0.11.dist-info/METADATA
objectgmsh-0.11.dist-info/WHEEL
objectgmsh-0.11.dist-info/top_level.txt
objectgmsh-0.11.dist-info/RECORD
