Metadata-Version: 2.1
Name: objectgmsh
Version: 0.11
Summary: Object oriented Gmsh modeling.
Home-page: https://github.com/nemocrys/objectgmsh
Author: Arved Enders-Seidlitz
Author-email: arved.enders-seidlitz@ikz-berlin.de
Classifier: Programming Language :: Python :: 3
Classifier: License :: OSI Approved :: GNU General Public License v3 or later (GPLv3+)
Classifier: Operating System :: OS Independent
Requires-Python: >=3.7
License-File: LICENSE
Requires-Dist: gmsh
Requires-Dist: numpy
